openpom/__init__.py
openpom/feat/__init__.py
openpom/feat/graph_featurizer.py
openpom/feat/test/__init__.py
openpom/feat/test/test_graph_featurizer.py
openpom/hyper/__init__.py
openpom/hyper/configs/__init__.py
openpom/hyper/configs/base_config.py
openpom/hyper/configs/model_configs.py
openpom/hyper/scripts/__init__.py
openpom/hyper/scripts/mpnnpom_random_cv.py
openpom/hyper/test/__init__.py
openpom/hyper/test/test_base_config.py
openpom/layers/__init__.py
openpom/layers/pom_ffn.py
openpom/layers/pom_mpnn_gnn.py
openpom/layers/test/__init__.py
openpom/layers/test/test_layers.py
openpom/models/__init__.py
openpom/models/mpnn_pom.py
openpom/models/test/__init__.py
openpom/models/test/test_mpnn_pom.py
openpom/models/test/test_mpnn_pom_model.py
openpom/utils/__init__.py
openpom/utils/data_utils.py
openpom/utils/loss.py
openpom/utils/molecule_feature_utils.py
openpom/utils/optimizer.py
openpom/utils/test/__init__.py
openpom/utils/test/test_data_utils.py
openpom/utils/test/test_feat_utils.py
openpom/utils/test/test_loss.py
openpom/utils/test/test_optimizer.py
openpom-1.0.0.dist-info/licenses/LICENSE
openpom-1.0.0.dist-info/METADATA
openpom-1.0.0.dist-info/WHEEL
openpom-1.0.0.dist-info/top_level.txt
openpom-1.0.0.dist-info/RECORD
