Metadata-Version: 2.4
Name: openpom
Version: 1.0.0
Summary: Open-source Principal Odor Map models for Olfaction
Author: Aryan Amit Barsainyan
Author-email: aryan.barsainyan@gmail.com
License: MIT
License-File: LICENSE
Requires-Dist: pyrfume
Requires-Dist: dgllife
Requires-Dist: pytest
Requires-Dist: ipykernel
Requires-Dist: scikit-multilearn
Requires-Dist: deepchem
Requires-Dist: torch
Requires-Dist: dgl
Dynamic: author
Dynamic: author-email
Dynamic: description
Dynamic: license
Dynamic: license-file
Dynamic: requires-dist
Dynamic: summary
